sequana_pipelines/ribofinder/__init__.py
sequana_pipelines/ribofinder/config.yaml
sequana_pipelines/ribofinder/dag.png
sequana_pipelines/ribofinder/main.py
sequana_pipelines/ribofinder/multiqc_config.yaml
sequana_pipelines/ribofinder/ribofinder.rules
sequana_pipelines/ribofinder/schema.yaml
sequana_pipelines/ribofinder/tools.txt
sequana_ribofinder-1.1.1.dist-info/LICENSE
sequana_ribofinder-1.1.1.dist-info/METADATA
sequana_ribofinder-1.1.1.dist-info/WHEEL
sequana_ribofinder-1.1.1.dist-info/entry_points.txt
sequana_ribofinder-1.1.1.dist-info/RECORD
